LICENSE
MANIFEST.in
README.md
pyproject.toml
setup.py
streamlit_folium/__init__.py
streamlit_folium_incaper.egg-info/PKG-INFO
streamlit_folium_incaper.egg-info/SOURCES.txt
streamlit_folium_incaper.egg-info/dependency_links.txt
streamlit_folium_incaper.egg-info/requires.txt
streamlit_folium_incaper.egg-info/top_level.txt